llm_lambda.py
llm_lambda-0.1.1.dist-info/LICENSE
llm_lambda-0.1.1.dist-info/METADATA
llm_lambda-0.1.1.dist-info/WHEEL
llm_lambda-0.1.1.dist-info/entry_points.txt
llm_lambda-0.1.1.dist-info/top_level.txt
llm_lambda-0.1.1.dist-info/RECORD
