Metadata-Version: 2.1
Name: llm-lambda
Version: 0.1.1
Summary: LLM access to LAMBDA's API
Author: Nick Mystic
License: Apache-2.0
Project-URL: Homepage, https://github.com/ghostofpokemon/llm-lambda
Project-URL: Issues, https://github.com/ghostofpokemon/llm-lambda/issues
Project-URL: CI, https://github.com/ghostofpokemon/llm-lambda/actions
Classifier: License :: OSI Approved :: Apache Software License
License-File: LICENSE
Requires-Dist: llm
Requires-Dist: httpx
Provides-Extra: test
Requires-Dist: pytest ; extra == 'test'
Requires-Dist: pytest-httpx ; extra == 'test'
